pyrad/__init__.py
pyrad/version.py
pyrad/flow/__init__.py
pyrad/flow/flow_aux.py
pyrad/flow/flow_control.py
pyrad/graph/__init__.py
pyrad/graph/plots.py
pyrad/graph/plots_aux.py
pyrad/graph/plots_grid.py
pyrad/graph/plots_spectra.py
pyrad/graph/plots_timeseries.py
pyrad/graph/plots_vol.py
pyrad/io/__init__.py
pyrad/io/config.py
pyrad/io/default_config.py
pyrad/io/flock_utils.py
pyrad/io/io_aux.py
pyrad/io/mxpol_config.py
pyrad/io/read_data_dem.py
pyrad/io/read_data_hzt.py
pyrad/io/read_data_icon.py
pyrad/io/read_data_iso0_mf.py
pyrad/io/read_data_mxpol.py
pyrad/io/read_data_other.py
pyrad/io/read_data_radar.py
pyrad/io/read_data_sensor.py
pyrad/io/read_data_sun.py
pyrad/io/test_write_monitoring.py
pyrad/io/timeseries.py
pyrad/io/trajectory.py
pyrad/io/write_data.py
pyrad/proc/__init__.py
pyrad/proc/process_Doppler.py
pyrad/proc/process_aux.py
pyrad/proc/process_calib.py
pyrad/proc/process_dem.py
pyrad/proc/process_echoclass.py
pyrad/proc/process_grid.py
pyrad/proc/process_icon.py
pyrad/proc/process_intercomp.py
pyrad/proc/process_iq.py
pyrad/proc/process_monitoring.py
pyrad/proc/process_phase.py
pyrad/proc/process_retrieve.py
pyrad/proc/process_spectra.py
pyrad/proc/process_timeseries.py
pyrad/proc/process_traj.py
pyrad/prod/__init__.py
pyrad/prod/process_grid_products.py
pyrad/prod/process_intercomp_products.py
pyrad/prod/process_monitoring_products.py
pyrad/prod/process_product.py
pyrad/prod/process_spectra_products.py
pyrad/prod/process_timeseries_products.py
pyrad/prod/process_traj_products.py
pyrad/prod/process_vol_products.py
pyrad/prod/product_aux.py
pyrad/util/__init__.py
pyrad/util/data_retrieval_utils.py
pyrad/util/debug_utils.py
pyrad/util/radar_utils.py
pyrad/util/stat_utils.py
pyrad_mch-2.1.2.data/scripts/common_colocated_gates.py
pyrad_mch-2.1.2.data/scripts/config_to_yaml.py
pyrad_mch-2.1.2.data/scripts/image_montage.py
pyrad_mch-2.1.2.data/scripts/main_precipitation_comparison.py
pyrad_mch-2.1.2.data/scripts/main_process_cosmo.py
pyrad_mch-2.1.2.dist-info/METADATA
pyrad_mch-2.1.2.dist-info/WHEEL
pyrad_mch-2.1.2.dist-info/top_level.txt
pyrad_mch-2.1.2.dist-info/RECORD
