Metadata-Version: 2.4
Name: pyrad_mch
Version: 2.1.2
Summary:  Python Radar Toolkit
Home-page: https://github.com/MeteoSwiss/pyrad.git
Author: MeteoSwiss Pyrad Developers
Author-email: daniel.wolfensberger@meteoswiss.ch
Maintainer: MeteoSwiss Pyrad Developers
Maintainer-email: daniel.wolfensberger@meteoswiss.ch
License: BSD
Platform: Linux
Classifier:     Development Status :: 5 - Production/Stable
Classifier:     Intended Audience :: Science/Research
Classifier:     Intended Audience :: Developers
Classifier:     License :: OSI Approved :: BSD License
Classifier:     Programming Language :: Python
Classifier:     Programming Language :: Python :: 3
Classifier:     Programming Language :: Python :: 3.6
Classifier:     Programming Language :: Python :: 3.7
Classifier:     Programming Language :: Python :: 3.8
Classifier:     Programming Language :: Python :: 3.9
Classifier:     Programming Language :: Python :: 3.10
Classifier:     Programming Language :: C
Classifier:     Programming Language :: Cython
Classifier:     Topic :: Scientific/Engineering
Classifier:     Topic :: Scientific/Engineering :: Atmospheric Science
Classifier:     Operating System :: POSIX :: Linux
Classifier:     Operating System :: MacOS :: MacOS X
Classifier:     Operating System :: Microsoft :: Windows
Classifier:     Framework :: Matplotlib
Dynamic: author
Dynamic: author-email
Dynamic: classifier
Dynamic: description
Dynamic: home-page
Dynamic: license
Dynamic: maintainer
Dynamic: maintainer-email
Dynamic: platform
Dynamic: summary
